topsis/__init__.py
topsis/topsis.py
topsis_antigravity_101010-1.0.0.dist-info/METADATA
topsis_antigravity_101010-1.0.0.dist-info/WHEEL
topsis_antigravity_101010-1.0.0.dist-info/entry_points.txt
topsis_antigravity_101010-1.0.0.dist-info/top_level.txt
topsis_antigravity_101010-1.0.0.dist-info/RECORD
