Metadata-Version: 2.4
Name: Topsis-Antigravity-101010
Version: 1.0.0
Summary: A Python package for TOPSIS implementation
Home-page: https://github.com/example/topsis
Author: Antigravity
Author-email: antigravity@example.com
Classifier: Programming Language :: Python :: 3
Classifier: License :: OSI Approved :: MIT License
Classifier: Operating System :: OS Independent
Requires-Python: >=3.6
Dynamic: author
Dynamic: author-email
Dynamic: classifier
Dynamic: description
Dynamic: description-content-type
Dynamic: home-page
Dynamic: requires-python
Dynamic: summary
